pyParz/__init__.py
pyParz/parallelize.py
pyParz/pyParz.py
pyParz/test_pyparz.py
pyParz-1.0.2.dist-info/METADATA
pyParz-1.0.2.dist-info/WHEEL
pyParz-1.0.2.dist-info/top_level.txt
pyParz-1.0.2.dist-info/RECORD
